[
  {
    "id": 401,
    "en": "Is Germany worth visiting?",
    "fa": "آیا آلمان ارزش دیدن داره؟"
  },
  {
    "id": 402,
    "en": "What do you suggest?",
    "fa": "چی پیشنهاد میدی؟"
  },
  {
    "id": 403,
    "en": "Fasten your seat belt (Buckle up)",
    "fa": "کمربندت را ببند"
  },
  {
    "id": 404,
    "en": "The greatest wealth is health",
    "fa": "بزرگترین ثروت سلامتی است"
  },
  {
    "id": 405,
    "en": "Didn't I tell you not to go out?",
    "fa": "بهت نگفتم بیرون نرو"
  },
  {
    "id": 406,
    "en": "There is nothing wrong with your laptop",
    "fa": "لپ تاپ شما هیچ مشکلی ندارد"
  },
  {
    "id": 407,
    "en": "What the hell do you want me to do?",
    "fa": "می خوای چه غلطی بکنم؟"
  },
  {
    "id": 408,
    "en": "Needless to say",
    "fa": "نیازی به گفتن نیست"
  },
  {
    "id": 409,
    "en": "I have called him several times since morning",
    "fa": "از صبح چندین بار با او تماس گرفتم"
  },
  {
    "id": 410,
    "en": "There's something on your face",
    "fa": "یه چیزی روی صورتت هست"
  },
  {
    "id": 411,
    "en": "I wish I could",
    "fa": "ای کاش میتونستم"
  },
  {
    "id": 412,
    "en": "Didn't you hear what I said?",
    "fa": "نشنیدی چی گفتم؟"
  },
  {
    "id": 413,
    "en": "By the way",
    "fa": "در ضمن"
  },
  {
    "id": 414,
    "en": "Will you be home late tonight?",
    "fa": "آیا دیر خانه خواهی بود؟"
  },
  {
    "id": 415,
    "en": "Let me show it to you",
    "fa": "بذار بهت نشون بدم"
  },
  {
    "id": 416,
    "en": "Has anyone been to see him in the hospital?",
    "fa": "آیا کسی برای دیدن او به بیمارستان رفته؟"
  },
  {
    "id": 417,
    "en": "I need to wear my shoes in",
    "fa": "من باید کفش هایم را بپوشم"
  },
  {
    "id": 418,
    "en": "I put on my hat",
    "fa": "کلاه سرم گذاشتم"
  },
  {
    "id": 419,
    "en": "I take off my hat",
    "fa": "کلاه از سرم در آوردم"
  },
  {
    "id": 420,
    "en": "Shall I try this shirt on?",
    "fa": "می تونم این پیراهن را تست کنم"
  },
  {
    "id": 421,
    "en": "How long does it take to go by bus?",
    "fa": "با اتوبوس چقدر طول می کشد؟"
  },
  {
    "id": 422,
    "en": "What color shirt do you want to buy?",
    "fa": "چه پیراهنی رنگی را می خواهید بخرید؟"
  },
  {
    "id": 423,
    "en": "I try not to let my problems at work carry over into my private life",
    "fa": "من سعی می کنم اجازه ندهم مشکلاتم در محل کار به زندگی خصوصیم بیاورم"
  },
  {
    "id": 424,
    "en": "I am going to try bungee jumping, but I get cold feet",
    "fa": "من قصد دارم پرش بانجی را امتحان کنم، اما می ترسم"
  },
  {
    "id": 425,
    "en": "How much is a letter with a stamp to Iran?",
    "fa": "یک نامه با یک تمبر به ایران چند است؟"
  },
  {
    "id": 426,
    "en": "It was busy last time",
    "fa": "دفعه آخر مشغول بود"
  },
  {
    "id": 427,
    "en": "Try again in a few minutes",
    "fa": "چند دقیقه دیگه دوباره امتحان کن"
  },
  {
    "id": 428,
    "en": "I tried a few times but the number is still busy",
    "fa": "یه چند دفعه امتحان کردم اما شماره هنوز اشغاله"
  },
  {
    "id": 429,
    "en": "I write a lot of letters as much as I can",
    "fa": "من یه عالمه نامه تا اونجایی که می تونم مینویسم"
  },
  {
    "id": 430,
    "en": "What time does our meeting start?",
    "fa": "جلسمون چه ساعتی شروع می شود؟"
  },
  {
    "id": 431,
    "en": "It's sometimes difficult to talk to children",
    "fa": "صحبت با کودکان گاهی دشوار است"
  },
  {
    "id": 432,
    "en": "How is your headache?",
    "fa": "سر دردت چطوره؟"
  },
  {
    "id": 433,
    "en": "My head is aching",
    "fa": "سرم داره درد می کند"
  },
  {
    "id": 434,
    "en": "Can you write it down for me on paper, please?",
    "fa": "میتونی برام روی کاغذ بنویسیش, لطفا؟"
  },
  {
    "id": 435,
    "en": "Look, it's snowing",
    "fa": "نگاه کن داره برف میاد"
  },
  {
    "id": 436,
    "en": "I called him but he didn't pick up",
    "fa": "بهش زنگ زدم اما برنداشت"
  },
  {
    "id": 437,
    "en": "I am broke",
    "fa": "پول ندارم (ورشکسته)"
  },
  {
    "id": 438,
    "en": "This is the best movie that I have ever seen",
    "fa": "این بهترین فیلمیه که تا به حال دیدم"
  },
  {
    "id": 439,
    "en": "Let it go",
    "fa": "ولش کن"
  },
  {
    "id": 440,
    "en": "Do you always talk like this?",
    "fa": "همیشه اینطوری حرف میزنی؟"
  },
  {
    "id": 441,
    "en": "It's not that hard",
    "fa": "آنقدرها هم سخت نیست"
  },
  {
    "id": 442,
    "en": "Do I look that bad?",
    "fa": "آیا آنقدر بد به نظر میام؟"
  },
  {
    "id": 443,
    "en": "I don't mean to disrespect",
    "fa": "قصد بی احترامی ندارم"
  },
  {
    "id": 444,
    "en": "Don't be like that",
    "fa": "اون جوری نباش"
  },
  {
    "id": 445,
    "en": "Time is more valuable than money",
    "fa": "زمان ارزشمندتر از پوله"
  },
  {
    "id": 446,
    "en": "This is the house where I grew up in",
    "fa": "این  خانه ای است که من در آن بزرگ شدم"
  },
  {
    "id": 447,
    "en": "What were you thinking?",
    "fa": "داشتی به چی فکر میکردی؟"
  },
  {
    "id": 448,
    "en": "You are making a big deal out of it",
    "fa": "خیلی داری بزرگش میکنی "
  },
  {
    "id": 449,
    "en": "I love you more than anything in the world",
    "fa": "من تو را بیشتر از هر چیزی در دنیا دوست دارم"
  },
  {
    "id": 450,
    "en": "Sooner or later",
    "fa": "دیر یا زود"
  },
  {
    "id": 451,
    "en": "Man dies after masturbating 62 times straight",
    "fa": "مردی پس از 62 بار خودارضایی مرد"
  },
  {
    "id": 452,
    "en": "Everyone else was convinced, but I remained skeptical",
    "fa": "همه متقاعد شده بودند، اما من همچنان شک داشتم"
  },
  {
    "id": 453,
    "en": "You pulled it off",
    "fa": "تو از پسش براومدی"
  },
  {
    "id": 454,
    "en": "So I wanna quote one of his jokes",
    "fa": "بنابراین می خوام یکی از شوخیاش را نقل کنم"
  },
  {
    "id": 455,
    "en": "May I join you?",
    "fa": "میشه بهتون ملحق شم؟"
  },
  {
    "id": 456,
    "en": "May I have a word?",
    "fa": "میشه یه چیزی بگم؟"
  },
  {
    "id": 457,
    "en": "May I ask a favor?",
    "fa": "میشه یه خواهشی کنم؟"
  },
  {
    "id": 458,
    "en": "May I have your attention?",
    "fa": "میشه توجهتون رو بدید به من؟"
  },
  {
    "id": 459,
    "en": "Who cut the cheese?",
    "fa": "کی چسید؟"
  },
  {
    "id": 460,
    "en": "Nature is calling me",
    "fa": "جیش دارم"
  },
  {
    "id": 461,
    "en": "I am on my period",
    "fa": "پریودم"
  },
  {
    "id": 462,
    "en": "I feel bloated",
    "fa": "احساس نفخ می کنم"
  },
  {
    "id": 463,
    "en": "He is on the edge",
    "fa": "اعصاب نداره"
  },
  {
    "id": 464,
    "en": "How dare you suggest such a thing?",
    "fa": "چطور جرات داری چنین چیزی را پیشنهاد کنی؟"
  },
  {
    "id": 465,
    "en": "How dare you interfere in my life?",
    "fa": "چطور جرات داری تو زندگی من دخالت کنی؟"
  },
  {
    "id": 466,
    "en": "How dare you disobey me?",
    "fa": "چطور جرات داری از من سرپیچی کنی؟"
  },
  {
    "id": 467,
    "en": "How dare you accuse me of lying?",
    "fa": "چطور جرات داری منو متهم کنی به دروغ؟"
  },
  {
    "id": 468,
    "en": "I'm afraid of you",
    "fa": "من می ترسم ازت"
  },
  {
    "id": 469,
    "en": "I'm afraid for you",
    "fa": "من نگرانتم"
  },
  {
    "id": 470,
    "en": "I'm afraid so",
    "fa": "می ترسم اینطور باشه"
  },
  {
    "id": 471,
    "en": "I'm afraid to do it",
    "fa": "میترسم انجامش بدم"
  },
  {
    "id": 472,
    "en": "I'm afraid, I can't",
    "fa": "میترسم نتونم"
  },
  {
    "id": 473,
    "en": "You left the door ajar",
    "fa": "در را بازگذاشتی"
  },
  {
    "id": 474,
    "en": "Draw the curtains",
    "fa": "پرده ها رو بکش"
  },
  {
    "id": 475,
    "en": "I would say so",
    "fa": "منم اینطور می گم"
  },
  {
    "id": 476,
    "en": "Look at how massive this ant is compared to my hand",
    "fa": "ببین این مورچه در مقایسه با دست من چقدر بزرگه"
  },
  {
    "id": 477,
    "en": "I am not even gonna think of how painful a bite from this ant would be",
    "fa": "حتی به این فکر نمی کنم که گاز گرفتن این مورچه چقدر دردناک خواهد بود"
  },
  {
    "id": 478,
    "en": "Did you just run out of gas?",
    "fa": "الان بنزینت تموم شده؟"
  },
  {
    "id": 479,
    "en": "The battery lasts well",
    "fa": "باتری خوب دوام میاره"
  },
  {
    "id": 480,
    "en": "I wanna thank me for trying to do more right than wrong",
    "fa": "میخواهم از خودم تشکر کنم که سعی کردم کارهای درست را بیشتر از اشتباه انجام بدم"
  },
  {
    "id": 481,
    "en": "I wanna thank me for always being a giver and trying to give more than I receive",
    "fa": "میخواهم از خودم تشکر کنم که همیشه بخشنده بودم و سعی کردم بیشتر از چیزی که دریافت میکنم بدم"
  },
  {
    "id": 482,
    "en": "It's an expression",
    "fa": "این یک اصطلاحه"
  },
  {
    "id": 483,
    "en": "Better safe than sorry",
    "fa": "احتیاط شرط عقله"
  },
  {
    "id": 484,
    "en": "Do you know each other?",
    "fa": "همدیگر را می شناسید؟"
  },
  {
    "id": 485,
    "en": "How did you find me?",
    "fa": "چطور منو پیدا کردی؟"
  },
  {
    "id": 486,
    "en": "Was your problem solved?",
    "fa": "مشکلت حل شد؟"
  },
  {
    "id": 487,
    "en": "Was anybody hurt in the accident?",
    "fa": "آیا کسی در تصادف آسیب دیده؟"
  },
  {
    "id": 488,
    "en": "Like it or not",
    "fa": "بخوای نخوای"
  },
  {
    "id": 489,
    "en": "Don't be late again",
    "fa": "ديگه دير نكن"
  },
  {
    "id": 490,
    "en": "We are here to help you",
    "fa": "ما اینجاییم که کمکت کنیم"
  },
  {
    "id": 491,
    "en": "Send him in",
    "fa": "بفرستش داخل"
  },
  {
    "id": 492,
    "en": "Simple as that",
    "fa": "به همین سادگی"
  },
  {
    "id": 493,
    "en": "Now you try",
    "fa": "حالا تو امتحان کن"
  },
  {
    "id": 494,
    "en": "Do you know what this means?",
    "fa": "می دونی این یعنی چی؟"
  },
  {
    "id": 495,
    "en": "We are ahead of schedule",
    "fa": "ما جلوتر از برنامه ایم"
  },
  {
    "id": 496,
    "en": "Do you know who they are?",
    "fa": "میدانی اونا کی هستند؟"
  },
  {
    "id": 497,
    "en": "How does it taste?",
    "fa": "مزه اش چطوره؟"
  },
  {
    "id": 498,
    "en": "We must do something",
    "fa": "باید یه کاری بکنیم"
  },
  {
    "id": 499,
    "en": "What did you learn in school today?",
    "fa": "امروز تو مدرسه چی یاد گرفتی؟"
  },
  {
    "id": 500,
    "en": "Whatever happens",
    "fa": "هر اتفاقی بیفته"
  },
  {
    "id": 501,
    "en": "Please excuse me I don't mean to be rude",
    "fa": "ببخشید قصد بی ادبی ندارم"
  },
  {
    "id": 502,
    "en": "He came by the apartment (came to the apartment) right after you left",
    "fa": "او بلافاصله بعد از رفتن شما به آپارتمان آمد"
  },
  {
    "id": 503,
    "en": "I was only gone 20 minutes",
    "fa": "فقط 20 دقیقه نبودم"
  },
  {
    "id": 504,
    "en": "It's not as bad as it sounds",
    "fa": "آنقدر هم که به نظر میاد بد نیست"
  },
  {
    "id": 505,
    "en": "I asked him how he came by the money (get the money), but he wouldn't tell me",
    "fa": "از او پرسیدم که چگونه این پول بدست آوردی، اما او به من نگفت"
  },
  {
    "id": 506,
    "en": "What are you waiting for?",
    "fa": "منتظر چی هستی؟"
  },
  {
    "id": 507,
    "en": "I thought you would help me but you didn't",
    "fa": "فکر می کردم به من کمک می کنی اما نکردی"
  },
  {
    "id": 508,
    "en": "You look tired",
    "fa": "خسته به نظر میای"
  },
  {
    "id": 509,
    "en": "Get ready",
    "fa": "آماده شو"
  },
  {
    "id": 510,
    "en": "What are you thinking about?",
    "fa": "به چی فکر میکنی؟"
  },
  {
    "id": 511,
    "en": "Is it actually true to some degree?",
    "fa": "آیا واقعاً تا حدی درسته؟"
  },
  {
    "id": 512,
    "en": "I was just informed",
    "fa": "همین الان مطلع شدم"
  },
  {
    "id": 513,
    "en": "It's really sore",
    "fa": "واقعاً دردناک است"
  },
  {
    "id": 514,
    "en": "He said can you tell me exactly where it hurts",
    "fa": "گفت میشه دقیقا بگی کجا درد میکنه"
  },
  {
    "id": 515,
    "en": "I used to think people switch jobs for money only",
    "fa": "من قبلاً فکر می کردم مردم فقط برای پول شغلشون را عوض می کنند "
  },
  {
    "id": 516,
    "en": "I believe most people are looking for respect and mental peace",
    "fa": "معتقدم اکثر مردم به دنبال احترام و آرامش روانی هستند"
  },
  {
    "id": 517,
    "en": "Does it have any side effect?",
    "fa": "عوارض جانبی هم داره؟"
  },
  {
    "id": 518,
    "en": "How could you do this to me?",
    "fa": "چطور تونستی این کار رو با من بکنی؟"
  },
  {
    "id": 519,
    "en": "What's going on here?",
    "fa": "اینجا چه خبره؟"
  },
  {
    "id": 520,
    "en": "It wasn't your fault",
    "fa": "تقصیر تو نبود"
  },
  {
    "id": 521,
    "en": "What are you worried about?",
    "fa": "درباره چی نگرانی؟"
  },
  {
    "id": 522,
    "en": "I owe you an apology",
    "fa": "یک عذرخواهی به شما بدهکارم"
  },
  {
    "id": 523,
    "en": "What do you do in your free time?",
    "fa": "در اوقات فراغت چه کار می کنی؟"
  },
  {
    "id": 524,
    "en": "Don't you know who I am",
    "fa": "نمیدونی کی هستم"
  },
  {
    "id": 525,
    "en": "Are you following me?",
    "fa": "منو دنبال میکنی؟"
  },
  {
    "id": 526,
    "en": "I have a bad feeling",
    "fa": "حس بدی دارم"
  },
  {
    "id": 527,
    "en": "What do you do for a living?",
    "fa": "برای امرار معاش چه کار می کنی؟"
  },
  {
    "id": 528,
    "en": "I just want to make sure",
    "fa": "فقط میخوام مطمئن بشم"
  },
  {
    "id": 529,
    "en": "I was about to die",
    "fa": "داشتم می مردم"
  },
  {
    "id": 530,
    "en": "How far along are you?",
    "fa": "چند وقت بارداری؟"
  },
  {
    "id": 531,
    "en": "You framed me",
    "fa": "برام پاپوش دوختی"
  },
  {
    "id": 532,
    "en": "I am getting dressed",
    "fa": "چند وقت بارداری؟"
  }
]
